{
  "generated_at": "2026-05-27 07:17 KST",
  "events": [
    {
      "date": "2026-05-29",
      "title": "MSCI 분기별 지수 리밸런싱 (Q2 2026)",
      "category": "market_structure",
      "importance": 4,
      "impact": [
        "equities"
      ],
      "consensus": null,
      "source_url": "https://www.msci.com/"
    },
    {
      "date": "2026-05-29",
      "title": "미국 선행 경제 지표 보고서 (국제 무역, 소매, 도매)",
      "category": "economic_data",
      "importance": 4,
      "impact": [
        "equities",
        "USD",
        "yields"
      ],
      "consensus": null,
      "source_url": "https://www.census.gov/"
    },
    {
      "date": "2026-06-01",
      "title": "미국 건설 지출 (건설 투자)",
      "category": "economic_data",
      "importance": 4,
      "impact": [
        "equities",
        "USD",
        "yields"
      ],
      "consensus": null,
      "source_url": "https://www.census.gov/"
    },
    {
      "date": "2026-06-01",
      "title": "미국 ISM 제조업 PMI",
      "category": "economic_data",
      "importance": 4,
      "impact": [
        "equities",
        "USD",
        "yields"
      ],
      "consensus": null,
      "source_url": "https://www.ismworld.org/"
    },
    {
      "date": "2026-06-02",
      "title": "마이크로소프트 빌드 2026 컨퍼런스 (1일차)",
      "category": "tech_conf",
      "importance": 4,
      "impact": [
        "equities"
      ],
      "consensus": null,
      "source_url": "https://www.microsoft.com/build/"
    },
    {
      "date": "2026-06-05",
      "title": "미국 비농업 고용보고서 (NFP)",
      "category": "economic_data",
      "importance": 5,
      "impact": [
        "VIX",
        "yields",
        "equities",
        "USD"
      ],
      "consensus": null,
      "source_url": "https://www.bls.gov/"
    },
    {
      "date": "2026-06-07",
      "title": "OPEC+ 장관급 회의",
      "category": "geopolitical",
      "importance": 4,
      "impact": [
        "oil",
        "equities"
      ],
      "consensus": null,
      "source_url": "https://www.opec.org/"
    },
    {
      "date": "2026-06-08",
      "title": "애플 WWDC 2026 키노트",
      "category": "tech_conf",
      "importance": 4,
      "impact": [
        "equities"
      ],
      "consensus": null,
      "source_url": "https://developer.apple.com/wwdc/"
    }
  ]
}